setup.py
geneparts/__init__.py
geneparts/test_ucsc.py
geneparts.egg-info/PKG-INFO
geneparts.egg-info/SOURCES.txt
geneparts.egg-info/dependency_links.txt
geneparts.egg-info/not-zip-safe
geneparts.egg-info/top_level.txt