Metadata-Version: 1.0
Name: geneparts
Version: 0.1
Summary: Tool to return different types of gene sequences.
Home-page: https://github.com/ericsho/geneparts
Author: Eric S. Ho
Author-email: hoe @ lafayette edu
License: UNKNOWN
Platform: UNKNOWN
